CHANGES.txt
LICENSE.txt
MANIFEST.in
README.txt
baserip.e4p
setup.py
.issues/.properties
baserip/__init__.py
baserip/baserip.py
baserip/command.py
baserip/dvd.py
baserip/encoders.py
baserip/forms.py
baserip/utils.py
baserip.egg-info/PKG-INFO
baserip.egg-info/SOURCES.txt
baserip.egg-info/dependency_links.txt
baserip.egg-info/entry_points.txt
baserip.egg-info/requires.txt
baserip.egg-info/top_level.txt
baserip/resources/__init__.py
baserip/resources/baserip.qrc
baserip/resources/baserip_rc.py
baserip/ui/Ui_br_mainwindow.py
baserip/ui/__init__.py
baserip/ui/br_jobdock.py
baserip/ui/br_mainwindow.py
baserip/ui/br_mainwindow.ui
docs/Makefile
docs/conf.py
docs/howto.rst
docs/index.rst
docs/motivation.rst
docs/overview.rst
docs/todo.rst
share/baserip.desktop
share/baserip.png